bbttest/__init__.py
bbttest/alg.py
bbttest/const.py
bbttest/model.py
bbttest/py_bbt.py
bbttest/utils.py
bbt_test-0.0.2.dist-info/WHEEL
bbt_test-0.0.2.dist-info/METADATA
bbt_test-0.0.2.dist-info/RECORD
