Metadata-Version: 2.3
Name: bbt-test
Version: 0.0.2
Summary: Bayesian Bradley-Terry model implementation in PyMC
Keywords: bayesian,bradley-terry model,multi-model comparison,multi-dataset comparison
Author: AGH ML & Cheminformatics Lab
Author-email: AGH ML & Cheminformatics Lab <praski@agh.edu.pl>
License: MIT
Classifier: Development Status :: 4 - Beta
Classifier: Environment :: Console
Classifier: Intended Audience :: Information Technology
Classifier: Intended Audience :: Science/Research
Classifier: License :: OSI Approved :: MIT License
Classifier: Programming Language :: Python :: 3.11
Classifier: Programming Language :: Python :: 3.12
Classifier: Programming Language :: Python :: 3.13
Classifier: Programming Language :: Python :: 3.14
Classifier: Topic :: Scientific/Engineering :: Artificial Intelligence
Classifier: Topic :: Utilities
Classifier: Typing :: Typed
Requires-Dist: pandas>=2.0.0
Requires-Dist: pymc
Requires-Dist: tqdm
Requires-Python: >=3.11
